{
  "info": {
    "name": "Password Reset with OTP",
    "_postman_id": "password-reset-otp-collection",
    "description": "Complete OTP-based password reset flow for Admin and Tenant users",
    "schema": "https://schema.getpostman.com/json/collection/v2.1.0/collection.json"
  },
  "variable": [
    {
      "key": "base_url",
      "value": "http://localhost:3000",
      "type": "string"
    },
    {
      "key": "admin_email",
      "value": "admin@example.com",
      "type": "string"
    },
    {
      "key": "tenant_email",
      "value": "user@restaurant.com",
      "type": "string"
    },
    {
      "key": "otp_code",
      "value": "",
      "type": "string"
    }
  ],
  "item": [
    {
      "name": "Admin Password Reset Flow",
      "item": [
        {
          "name": "1. Request OTP (Admin)",
          "event": [
            {
              "listen": "test",
              "script": {
                "exec": [
                  "if (pm.response.code === 200) {",
                  "    console.log('✅ OTP sent successfully');",
                  "    console.log('📧 Check email for OTP code');",
                  "}"
                ],
                "type": "text/javascript"
              }
            }
          ],
          "request": {
            "method": "POST",
            "header": [
              {
                "key": "Content-Type",
                "value": "application/json"
              }
            ],
            "body": {
              "mode": "raw",
              "raw": "{\n  \"email\": \"{{admin_email}}\"\n}"
            },
            "url": {
              "raw": "{{base_url}}/auth/password-reset/request-otp",
              "host": ["{{base_url}}"],
              "path": ["auth", "password-reset", "request-otp"]
            },
            "description": "Request a 6-digit OTP for admin password reset. OTP is sent to the email and expires in 10 minutes."
          },
          "response": [
            {
              "name": "Success Response",
              "originalRequest": {
                "method": "POST",
                "header": [],
                "body": {
                  "mode": "raw",
                  "raw": "{\n  \"email\": \"admin@example.com\"\n}"
                },
                "url": {
                  "raw": "{{base_url}}/auth/password-reset/request-otp",
                  "host": ["{{base_url}}"],
                  "path": ["auth", "password-reset", "request-otp"]
                }
              },
              "status": "OK",
              "code": 200,
              "_postman_previewlanguage": "json",
              "header": [],
              "cookie": [],
              "body": "{\n  \"status\": 200,\n  \"message\": \"OTP sent to your email. Please check your inbox.\",\n  \"result\": {\n    \"email\": \"admin@example.com\",\n    \"expiresIn\": \"10 minutes\",\n    \"expiresAt\": \"2026-01-07T12:10:00.000Z\"\n  }\n}"
            }
          ]
        },
        {
          "name": "2. Verify OTP (Admin)",
          "event": [
            {
              "listen": "test",
              "script": {
                "exec": [
                  "if (pm.response.code === 200) {",
                  "    console.log('✅ OTP verified successfully');",
                  "    console.log('🔓 You can now reset your password');",
                  "}"
                ],
                "type": "text/javascript"
              }
            }
          ],
          "request": {
            "method": "POST",
            "header": [
              {
                "key": "Content-Type",
                "value": "application/json"
              }
            ],
            "body": {
              "mode": "raw",
              "raw": "{\n  \"email\": \"{{admin_email}}\",\n  \"otp\": \"{{otp_code}}\"\n}"
            },
            "url": {
              "raw": "{{base_url}}/auth/password-reset/verify-otp",
              "host": ["{{base_url}}"],
              "path": ["auth", "password-reset", "verify-otp"]
            },
            "description": "Verify the 6-digit OTP received via email. You have 5 attempts before the OTP is invalidated."
          },
          "response": [
            {
              "name": "Success Response",
              "originalRequest": {
                "method": "POST",
                "header": [],
                "body": {
                  "mode": "raw",
                  "raw": "{\n  \"email\": \"admin@example.com\",\n  \"otp\": \"123456\"\n}"
                },
                "url": {
                  "raw": "{{base_url}}/auth/password-reset/verify-otp",
                  "host": ["{{base_url}}"],
                  "path": ["auth", "password-reset", "verify-otp"]
                }
              },
              "status": "OK",
              "code": 200,
              "_postman_previewlanguage": "json",
              "header": [],
              "cookie": [],
              "body": "{\n  \"status\": 200,\n  \"message\": \"OTP verified successfully. You can now reset your password.\",\n  \"result\": {\n    \"email\": \"admin@example.com\",\n    \"verified\": true,\n    \"userType\": \"admin\",\n    \"tenantSlug\": null\n  }\n}"
            }
          ]
        },
        {
          "name": "3. Reset Password (Admin)",
          "event": [
            {
              "listen": "test",
              "script": {
                "exec": [
                  "if (pm.response.code === 200) {",
                  "    console.log('✅ Password reset successful');",
                  "    console.log('🔐 You can now login with your new password');",
                  "}"
                ],
                "type": "text/javascript"
              }
            }
          ],
          "request": {
            "method": "POST",
            "header": [
              {
                "key": "Content-Type",
                "value": "application/json"
              }
            ],
            "body": {
              "mode": "raw",
              "raw": "{\n  \"email\": \"{{admin_email}}\",\n  \"password\": \"NewSecurePass123!\"\n}"
            },
            "url": {
              "raw": "{{base_url}}/auth/password-reset/reset",
              "host": ["{{base_url}}"],
              "path": ["auth", "password-reset", "reset"]
            },
            "description": "Reset password after OTP verification. The OTP is marked as used and cannot be reused."
          },
          "response": [
            {
              "name": "Success Response",
              "originalRequest": {
                "method": "POST",
                "header": [],
                "body": {
                  "mode": "raw",
                  "raw": "{\n  \"email\": \"admin@example.com\",\n  \"password\": \"NewSecurePass123!\"\n}"
                },
                "url": {
                  "raw": "{{base_url}}/auth/password-reset/reset",
                  "host": ["{{base_url}}"],
                  "path": ["auth", "password-reset", "reset"]
                }
              },
              "status": "OK",
              "code": 200,
              "_postman_previewlanguage": "json",
              "header": [],
              "cookie": [],
              "body": "{\n  \"status\": 200,\n  \"message\": \"Password reset successful. You can now login with your new password.\",\n  \"result\": {\n    \"email\": \"admin@example.com\"\n  }\n}"
            }
          ]
        }
      ],
      "description": "Complete password reset flow for Admin users using OTP verification"
    },
    {
      "name": "Tenant Password Reset Flow",
      "item": [
        {
          "name": "1. Request OTP (Tenant)",
          "event": [
            {
              "listen": "test",
              "script": {
                "exec": [
                  "if (pm.response.code === 200) {",
                  "    console.log('✅ OTP sent successfully');",
                  "    console.log('📧 Check email for OTP code');",
                  "    console.log('🏢 Tenant resolved from email domain');",
                  "}"
                ],
                "type": "text/javascript"
              }
            }
          ],
          "request": {
            "method": "POST",
            "header": [
              {
                "key": "Content-Type",
                "value": "application/json"
              }
            ],
            "body": {
              "mode": "raw",
              "raw": "{\n  \"email\": \"{{tenant_email}}\"\n}"
            },
            "url": {
              "raw": "{{base_url}}/t/auth/password-reset/request-otp",
              "host": ["{{base_url}}"],
              "path": ["t", "auth", "password-reset", "request-otp"]
            },
            "description": "Request a 6-digit OTP for tenant password reset. Tenant is automatically resolved from email domain (e.g., user@restaurant.com → tenant: restaurant)."
          },
          "response": [
            {
              "name": "Success Response",
              "originalRequest": {
                "method": "POST",
                "header": [],
                "body": {
                  "mode": "raw",
                  "raw": "{\n  \"email\": \"user@restaurant.com\"\n}"
                },
                "url": {
                  "raw": "{{base_url}}/t/auth/password-reset/request-otp",
                  "host": ["{{base_url}}"],
                  "path": ["t", "auth", "password-reset", "request-otp"]
                }
              },
              "status": "OK",
              "code": 200,
              "_postman_previewlanguage": "json",
              "header": [],
              "cookie": [],
              "body": "{\n  \"status\": 200,\n  \"message\": \"OTP sent to your email. Please check your inbox.\",\n  \"result\": {\n    \"email\": \"user@restaurant.com\",\n    \"expiresIn\": \"10 minutes\",\n    \"expiresAt\": \"2026-01-07T12:10:00.000Z\"\n  }\n}"
            }
          ]
        },
        {
          "name": "2. Verify OTP (Tenant)",
          "event": [
            {
              "listen": "test",
              "script": {
                "exec": [
                  "if (pm.response.code === 200) {",
                  "    console.log('✅ OTP verified successfully');",
                  "    console.log('🔓 You can now reset your password');",
                  "}"
                ],
                "type": "text/javascript"
              }
            }
          ],
          "request": {
            "method": "POST",
            "header": [
              {
                "key": "Content-Type",
                "value": "application/json"
              }
            ],
            "body": {
              "mode": "raw",
              "raw": "{\n  \"email\": \"{{tenant_email}}\",\n  \"otp\": \"{{otp_code}}\"\n}"
            },
            "url": {
              "raw": "{{base_url}}/t/auth/password-reset/verify-otp",
              "host": ["{{base_url}}"],
              "path": ["t", "auth", "password-reset", "verify-otp"]
            },
            "description": "Verify the 6-digit OTP received via email. You have 5 attempts before the OTP is invalidated."
          },
          "response": [
            {
              "name": "Success Response",
              "originalRequest": {
                "method": "POST",
                "header": [],
                "body": {
                  "mode": "raw",
                  "raw": "{\n  \"email\": \"user@restaurant.com\",\n  \"otp\": \"123456\"\n}"
                },
                "url": {
                  "raw": "{{base_url}}/t/auth/password-reset/verify-otp",
                  "host": ["{{base_url}}"],
                  "path": ["t", "auth", "password-reset", "verify-otp"]
                }
              },
              "status": "OK",
              "code": 200,
              "_postman_previewlanguage": "json",
              "header": [],
              "cookie": [],
              "body": "{\n  \"status\": 200,\n  \"message\": \"OTP verified successfully. You can now reset your password.\",\n  \"result\": {\n    \"email\": \"user@restaurant.com\",\n    \"verified\": true,\n    \"userType\": \"tenant\",\n    \"tenantSlug\": \"restaurant\"\n  }\n}"
            }
          ]
        },
        {
          "name": "3. Reset Password (Tenant)",
          "event": [
            {
              "listen": "test",
              "script": {
                "exec": [
                  "if (pm.response.code === 200) {",
                  "    console.log('✅ Password reset successful');",
                  "    console.log('🔐 You can now login with your new password');",
                  "}"
                ],
                "type": "text/javascript"
              }
            }
          ],
          "request": {
            "method": "POST",
            "header": [
              {
                "key": "Content-Type",
                "value": "application/json"
              }
            ],
            "body": {
              "mode": "raw",
              "raw": "{\n  \"email\": \"{{tenant_email}}\",\n  \"password\": \"NewSecurePass123!\"\n}"
            },
            "url": {
              "raw": "{{base_url}}/t/auth/password-reset/reset",
              "host": ["{{base_url}}"],
              "path": ["t", "auth", "password-reset", "reset"]
            },
            "description": "Reset password after OTP verification. The OTP is marked as used and cannot be reused."
          },
          "response": [
            {
              "name": "Success Response",
              "originalRequest": {
                "method": "POST",
                "header": [],
                "body": {
                  "mode": "raw",
                  "raw": "{\n  \"email\": \"user@restaurant.com\",\n  \"password\": \"NewSecurePass123!\"\n}"
                },
                "url": {
                  "raw": "{{base_url}}/t/auth/password-reset/reset",
                  "host": ["{{base_url}}"],
                  "path": ["t", "auth", "password-reset", "reset"]
                }
              },
              "status": "OK",
              "code": 200,
              "_postman_previewlanguage": "json",
              "header": [],
              "cookie": [],
              "body": "{\n  \"status\": 200,\n  \"message\": \"Password reset successful. You can now login with your new password.\",\n  \"result\": {\n    \"email\": \"user@restaurant.com\",\n    \"tenantSlug\": \"restaurant\"\n  }\n}"
            }
          ]
        }
      ],
      "description": "Complete password reset flow for Tenant users using OTP verification. Tenant is automatically resolved from email domain."
    },
    {
      "name": "Error Scenarios",
      "item": [
        {
          "name": "Rate Limit Exceeded",
          "request": {
            "method": "POST",
            "header": [
              {
                "key": "Content-Type",
                "value": "application/json"
              }
            ],
            "body": {
              "mode": "raw",
              "raw": "{\n  \"email\": \"{{admin_email}}\"\n}"
            },
            "url": {
              "raw": "{{base_url}}/auth/password-reset/request-otp",
              "host": ["{{base_url}}"],
              "path": ["auth", "password-reset", "request-otp"]
            },
            "description": "Attempting to request OTP more than 3 times in 15 minutes will result in rate limiting."
          },
          "response": [
            {
              "name": "Rate Limit Error",
              "originalRequest": {
                "method": "POST",
                "header": [],
                "body": {
                  "mode": "raw",
                  "raw": "{\n  \"email\": \"admin@example.com\"\n}"
                },
                "url": {
                  "raw": "{{base_url}}/auth/password-reset/request-otp",
                  "host": ["{{base_url}}"],
                  "path": ["auth", "password-reset", "request-otp"]
                }
              },
              "status": "Too Many Requests",
              "code": 429,
              "_postman_previewlanguage": "json",
              "header": [],
              "cookie": [],
              "body": "{\n  \"status\": 429,\n  \"message\": \"Too many requests. Please try again in 15 minutes.\"\n}"
            }
          ]
        },
        {
          "name": "Invalid OTP",
          "request": {
            "method": "POST",
            "header": [
              {
                "key": "Content-Type",
                "value": "application/json"
              }
            ],
            "body": {
              "mode": "raw",
              "raw": "{\n  \"email\": \"{{admin_email}}\",\n  \"otp\": \"999999\"\n}"
            },
            "url": {
              "raw": "{{base_url}}/auth/password-reset/verify-otp",
              "host": ["{{base_url}}"],
              "path": ["auth", "password-reset", "verify-otp"]
            },
            "description": "Providing an incorrect OTP will decrement remaining attempts."
          },
          "response": [
            {
              "name": "Invalid OTP Error",
              "originalRequest": {
                "method": "POST",
                "header": [],
                "body": {
                  "mode": "raw",
                  "raw": "{\n  \"email\": \"admin@example.com\",\n  \"otp\": \"999999\"\n}"
                },
                "url": {
                  "raw": "{{base_url}}/auth/password-reset/verify-otp",
                  "host": ["{{base_url}}"],
                  "path": ["auth", "password-reset", "verify-otp"]
                }
              },
              "status": "Bad Request",
              "code": 400,
              "_postman_previewlanguage": "json",
              "header": [],
              "cookie": [],
              "body": "{\n  \"status\": 400,\n  \"message\": \"Invalid OTP. 4 attempt(s) remaining.\"\n}"
            }
          ]
        },
        {
          "name": "No Verified OTP",
          "request": {
            "method": "POST",
            "header": [
              {
                "key": "Content-Type",
                "value": "application/json"
              }
            ],
            "body": {
              "mode": "raw",
              "raw": "{\n  \"email\": \"{{admin_email}}\",\n  \"password\": \"NewSecurePass123!\"\n}"
            },
            "url": {
              "raw": "{{base_url}}/auth/password-reset/reset",
              "host": ["{{base_url}}"],
              "path": ["auth", "password-reset", "reset"]
            },
            "description": "Attempting to reset password without verifying OTP first."
          },
          "response": [
            {
              "name": "No Verified OTP Error",
              "originalRequest": {
                "method": "POST",
                "header": [],
                "body": {
                  "mode": "raw",
                  "raw": "{\n  \"email\": \"admin@example.com\",\n  \"password\": \"NewSecurePass123!\"\n}"
                },
                "url": {
                  "raw": "{{base_url}}/auth/password-reset/reset",
                  "host": ["{{base_url}}"],
                  "path": ["auth", "password-reset", "reset"]
                }
              },
              "status": "Bad Request",
              "code": 400,
              "_postman_previewlanguage": "json",
              "header": [],
              "cookie": [],
              "body": "{\n  \"status\": 400,\n  \"message\": \"No verified OTP found. Please request and verify an OTP first.\"\n}"
            }
          ]
        }
      ],
      "description": "Common error scenarios and their responses"
    }
  ]
}

